{
  "kind": "singleType",
  "collectionName": "s03_profile_cards",
  "info": {
    "singularName": "s03-profile-card",
    "pluralName": "s03-profile-cards",
    "displayName": "Profile Card",
    "description": ""
  },
  "options": {
    "draftAndPublish": true
  },
  "pluginOptions": {},
  "attributes": {
    "Name": {
      "type": "string"
    },
    "Title": {
      "type": "string"
    },
    "Image": {
      "type": "media",
      "multiple": true,
      "required": false,
      "allowedTypes": [
        "images"
      ]
    }
  }
}
